ml_shrey/__init__.py
ml_shrey/backpropogation.py
ml_shrey/candidate.py
ml_shrey/id3_algo.py
ml_shrey/kmeans.py
ml_shrey/knn.py
ml_shrey/lwlr.py
ml_shrey/navie_bayes.py
ml_shrey/randomforest.py
ml_shrey/svm.py
ml_shrey-1.5.dist-info/METADATA
ml_shrey-1.5.dist-info/WHEEL
ml_shrey-1.5.dist-info/top_level.txt
ml_shrey-1.5.dist-info/RECORD
