Metadata-Version: 2.4
Name: ml_shrey
Version: 1.5
Summary: ML algorithms as Python package
Author-email: Shreyas <ishreyasr@gmail.com>
License-Expression: MIT
Project-URL: Homepage, https://github.com/ishreyasr/ml_shrey
Requires-Python: >=3.6
Requires-Dist: pandas
Requires-Dist: scikit-learn
Requires-Dist: matplotlib
Requires-Dist: numpy
